MANIFEST.in
Readme.md
dev-requirements.frozen.txt
dev-requirements.txt
licence.txt
noxfile.py
requirements.frozen.txt
requirements.txt
setup.cfg
setup.py
pandas_ta_quant/__init__.py
pandas_ta_quant/_decorators.py
pandas_ta_quant/_utils.py
pandas_ta_quant/pandas_patch.py
pandas_ta_quant.egg-info/PKG-INFO
pandas_ta_quant.egg-info/SOURCES.txt
pandas_ta_quant.egg-info/dependency_links.txt
pandas_ta_quant.egg-info/requires.txt
pandas_ta_quant.egg-info/top_level.txt
pandas_ta_quant/portfolio/__init__.py
pandas_ta_quant/portfolio/portfolio.py
pandas_ta_quant/portfolio/price.py
pandas_ta_quant/technical_analysis/__init__.py
pandas_ta_quant/technical_analysis/bands.py
pandas_ta_quant/technical_analysis/covariances.py
pandas_ta_quant/technical_analysis/edge_detect.py
pandas_ta_quant/technical_analysis/filters.py
pandas_ta_quant/technical_analysis/math.py
pandas_ta_quant/technical_analysis/meta.py
pandas_ta_quant/technical_analysis/normalizer.py
pandas_ta_quant/technical_analysis/encoders/__init__.py
pandas_ta_quant/technical_analysis/encoders/candles.py
pandas_ta_quant/technical_analysis/encoders/resample.py
pandas_ta_quant/technical_analysis/encoders/volume.py
pandas_ta_quant/technical_analysis/forecast/__init__.py
pandas_ta_quant/technical_analysis/forecast/predictive_indicator.py
pandas_ta_quant/technical_analysis/forecast/support.py
pandas_ta_quant/technical_analysis/forecast/volatility.py
pandas_ta_quant/technical_analysis/indicators/__init__.py
pandas_ta_quant/technical_analysis/indicators/multi_object.py
pandas_ta_quant/technical_analysis/indicators/single_object.py
pandas_ta_quant/technical_analysis/indicators/time.py
pandas_ta_quant_test/__init__.py
pandas_ta_quant_test/check_links.py
pandas_ta_quant_test/config.py
pandas_ta_quant_test/test__utils.py
pandas_ta_quant_test/test_multiindex_rows.py
pandas_ta_quant_test/test_notebooks.py
pandas_ta_quant_test/test_patching.py
pandas_ta_quant_test/portfolio/__init__.py
pandas_ta_quant_test/portfolio/test__portfolio.py
pandas_ta_quant_test/portfolio/test__price.py
pandas_ta_quant_test/technical_analysis/__init__.py
pandas_ta_quant_test/technical_analysis/test_covariances.py
