Metadata-Version: 2.1
Name: pandas-ta-quant
Version: 0.2.5
Summary: Augment pandas DataFrame with methods for machine learning
Home-page: https://github.com/KIC/pandas-ml-quant/pandas-ta-quant
Author: KIC
Author-email: 
License: MIT
Keywords: pandas,ml,util,quant
Platform: UNKNOWN
Classifier: Development Status :: 3 - Alpha
Classifier: Intended Audience :: Developers
Classifier: Topic :: Software Development :: Build Tools
Classifier: License :: OSI Approved :: MIT License
Classifier: Programming Language :: Python :: 3
Classifier: Programming Language :: Python :: 3.8
Provides-Extra: dev
